{
    "example_source": [
        "▁我还",
        "澄清",
        "了",
        "在该",
        "会议上",
        "提出的",
        "若干",
        "事项",
        "。"
    ],
    "example_target": [
        "<s>",
        "▁i",
        "▁was",
        "▁able",
        "▁to",
        "▁provide",
        "▁clarification",
        "▁on",
        "▁some",
        "▁of",
        "▁the",
        "▁matters",
        "▁which",
        "▁were",
        "▁raised",
        "▁at",
        "▁that",
        "▁meeting",
        ".",
        "</s>"
    ],
    "hypotheses": [
        {
            "hypothesis": [
                "▁i",
                "▁would",
                "▁also",
                "▁like",
                "▁to",
                "▁clarify",
                "▁a",
                "▁number",
                "▁of",
                "▁matters",
                "▁raised",
                "▁by",
                "▁the",
                "▁meeting",
                "."
            ],
            "score": -11.078287124633789
        },
        {
            "hypothesis": [
                "▁i",
                "▁also",
                "▁clarify",
                "▁a",
                "▁number",
                "▁of",
                "▁matters",
                "▁that",
                "▁have",
                "▁been",
                "▁raised",
                "▁in",
                "▁the",
                "▁meeting",
                "."
            ],
            "score": -11.16478443145752
        },
        {
            "hypothesis": [
                "▁i",
                "▁also",
                "▁clarify",
                "▁a",
                "▁number",
                "▁of",
                "▁matters",
                "▁that",
                "▁have",
                "▁been",
                "▁raised",
                "▁in",
                "▁that",
                "▁meeting",
                "."
            ],
            "score": -11.56063175201416
        },
        {
            "hypothesis": [
                "▁i",
                "▁also",
                "▁clarify",
                "▁a",
                "▁number",
                "▁of",
                "▁matters",
                "▁that",
                "▁have",
                "▁been",
                "▁raised",
                "▁in",
                "▁the",
                "▁conference",
                "."
            ],
            "score": -11.902853965759277
        },
        {
            "hypothesis": [
                "▁i",
                "▁would",
                "▁also",
                "▁like",
                "▁to",
                "▁clarify",
                "▁a",
                "▁number",
                "▁of",
                "▁matters",
                "▁raised",
                "▁by",
                "▁the",
                "▁conference",
                "."
            ],
            "score": -11.983582496643066
        },
        {
            "hypothesis": [
                "▁i",
                "▁have",
                "▁also",
                "▁clarified",
                "▁a",
                "▁number",
                "▁of",
                "▁matters",
                "▁that",
                "▁have",
                "▁been",
                "▁raised",
                "▁in",
                "▁the",
                "▁meeting",
                "."
            ],
            "score": -12.17946720123291
        },
        {
            "hypothesis": [
                "▁i",
                "▁would",
                "▁also",
                "▁like",
                "▁to",
                "▁clarify",
                "▁a",
                "▁number",
                "▁of",
                "▁matters",
                "▁that",
                "▁have",
                "▁been",
                "▁raised",
                "▁in",
                "▁the",
                "▁meeting",
                "."
            ],
            "score": -13.294999122619629
        },
        {
            "hypothesis": [
                "▁i",
                "▁would",
                "▁also",
                "▁like",
                "▁to",
                "▁clarify",
                "▁a",
                "▁number",
                "▁of",
                "▁matters",
                "▁that",
                "▁have",
                "▁been",
                "▁raised",
                "▁in",
                "▁that",
                "▁meeting",
                "."
            ],
            "score": -13.732470512390137
        },
        {
            "hypothesis": [
                "▁i",
                "▁would",
                "▁also",
                "▁like",
                "▁to",
                "▁clarify",
                "▁a",
                "▁number",
                "▁of",
                "▁matters",
                "▁that",
                "▁have",
                "▁been",
                "▁raised",
                "▁in",
                "▁the",
                "▁conference",
                "."
            ],
            "score": -14.099344253540039
        },
        {
            "hypothesis": [
                "▁i",
                "▁have",
                "▁also",
                "▁clarified",
                "▁a",
                "▁number",
                "▁of",
                "▁matters",
                "▁that",
                "▁have",
                "▁been",
                "▁raised",
                "▁in",
                "▁the",
                "▁meeting",
                "▁of",
                "▁the",
                "▁meeting",
                "."
            ],
            "score": -14.437121391296387
        }
    ],
    "diagnostic_info": "eyJ0IjogIjIwMjQtMTEtMTNUMTM6MzE6MTMuNTAxODUzIiwgImgiOiAiU2VyMSIsICJ1IjogInJvYXJrIn0="
}